yaml_config_day/__init__.py
yaml_config_day/config_manager.py
yaml_config_day-0.0.5.dist-info/LICENSE
yaml_config_day-0.0.5.dist-info/METADATA
yaml_config_day-0.0.5.dist-info/WHEEL
yaml_config_day-0.0.5.dist-info/entry_points.txt
yaml_config_day-0.0.5.dist-info/top_level.txt
yaml_config_day-0.0.5.dist-info/RECORD
