Metadata-Version: 2.1
Name: yaml-config-day
Version: 0.0.5
Summary: A Python library for managing project yaml secrets configurations
Home-page: https://github.com/Daylily-Informatics/yaml_config_day
Author: John Major
Author-email: john@daylilyinformatics.com
License-File: LICENSE
Requires-Dist: pyyaml
